odoo/addons/l10n_it_riba/README.rst
odoo/addons/l10n_it_riba/__init__.py
odoo/addons/l10n_it_riba/__manifest__.py
odoo/addons/l10n_it_riba/hooks.py
odoo/addons/l10n_it_riba/data/riba_sequence.xml
odoo/addons/l10n_it_riba/demo/riba_demo.xml
odoo/addons/l10n_it_riba/i18n/it.po
odoo/addons/l10n_it_riba/i18n/l10n_it_riba.pot
odoo/addons/l10n_it_riba/migrations/16.0.1.0.0/post-migrate.py
odoo/addons/l10n_it_riba/migrations/16.0.1.0.0/pre-migrate.py
odoo/addons/l10n_it_riba/migrations/16.0.1.0.0/data/noupdate.xml
odoo/addons/l10n_it_riba/models/__init__.py
odoo/addons/l10n_it_riba/models/account.py
odoo/addons/l10n_it_riba/models/account_config.py
odoo/addons/l10n_it_riba/models/ir_ui_menu.py
odoo/addons/l10n_it_riba/models/partner.py
odoo/addons/l10n_it_riba/models/riba.py
odoo/addons/l10n_it_riba/models/riba_config.py
odoo/addons/l10n_it_riba/readme/CONFIGURE.md
odoo/addons/l10n_it_riba/readme/CONTRIBUTORS.md
odoo/addons/l10n_it_riba/readme/DESCRIPTION.md
odoo/addons/l10n_it_riba/readme/USAGE.md
odoo/addons/l10n_it_riba/report/__init__.py
odoo/addons/l10n_it_riba/report/report.xml
odoo/addons/l10n_it_riba/report/slip_qweb.py
odoo/addons/l10n_it_riba/security/ir.model.access.csv
odoo/addons/l10n_it_riba/security/riba_security.xml
odoo/addons/l10n_it_riba/static/description/icon.png
odoo/addons/l10n_it_riba/static/description/index.html
odoo/addons/l10n_it_riba/tests/__init__.py
odoo/addons/l10n_it_riba/tests/riba_common.py
odoo/addons/l10n_it_riba/tests/test_account_move.py
odoo/addons/l10n_it_riba/tests/test_menu.py
odoo/addons/l10n_it_riba/tests/test_riba.py
odoo/addons/l10n_it_riba/views/account_config_view.xml
odoo/addons/l10n_it_riba/views/account_view.xml
odoo/addons/l10n_it_riba/views/configuration_view.xml
odoo/addons/l10n_it_riba/views/partner_view.xml
odoo/addons/l10n_it_riba/views/riba_detail_view.xml
odoo/addons/l10n_it_riba/views/riba_view.xml
odoo/addons/l10n_it_riba/views/slip_report.xml
odoo/addons/l10n_it_riba/views/wizard_credit.xml
odoo_addon_l10n_it_riba-16.0.1.10.1.dist-info/METADATA
odoo_addon_l10n_it_riba-16.0.1.10.1.dist-info/WHEEL
odoo_addon_l10n_it_riba-16.0.1.10.1.dist-info/top_level.txt
odoo_addon_l10n_it_riba-16.0.1.10.1.dist-info/RECORD
